cssselect2/__init__.py
cssselect2/compiler.py
cssselect2/parser.py
cssselect2/tree.py
cssselect2-0.4.0.dist-info/LICENSE
cssselect2-0.4.0.dist-info/WHEEL
cssselect2-0.4.0.dist-info/METADATA
cssselect2-0.4.0.dist-info/RECORD
